Metadata-Version: 2.1
Name: sl-zerobounce
Version: 0.1.4
Summary: ZeroBounce Python API - https://www.zerobounce.net.
Home-page: http://github.com/zerobounce/zerobounce-python-api
Author: Tudor Aursulesei
Author-email: tudor@zerobounce.net
License: UNKNOWN
Download-URL: https://github.com/zerobounce/zerobounce-python-api/archive/0.1.4.tar.gz
Keywords: email,validation
Platform: UNKNOWN
Classifier: Development Status :: 4 - Beta
Classifier: Intended Audience :: Developers
Classifier: License :: OSI Approved :: MIT License
Classifier: Operating System :: OS Independent
Classifier: Programming Language :: Python
